[
  {
    "line": 6,
    "elements": [
      {
        "before": [
          {
            "result": {
              "duration": 13285476277,
              "status": "passed"
            },
            "match": {
              "location": "Hook.setup(Scenario)"
            }
          }
        ],
        "line": 26,
        "name": "Verify that user should be able to set up a deadline for new task.",
        "description": "",
        "id": "activity-stream;verify-that-user-should-be-able-to-set-up-a-deadline-for-new-task.",
        "type": "scenario",
        "keyword": "Scenario",
        "steps": [
          {
            "result": {
              "duration": 16503081386,
              "status": "passed"
            },
            "line": 28,
            "name": "user logs in as a \"hr\"",
            "match": {
              "arguments": [
                {
                  "val": "\"hr\"",
                  "offset": 18
                }
              ],
              "location": "LoginStepDefinitions.user_logs_in_as_a(String)"
            },
            "keyword": "Given "
          },
          {
            "result": {
              "duration": 427176741,
              "status": "passed"
            },
            "line": 29,
            "name": "user clicks on Task",
            "match": {
              "location": "ActivityStreamStepDefinitions.user_clicks_on_Task()"
            },
            "keyword": "When "
          },
          {
            "result": {
              "duration": 9918707081,
              "status": "passed"
            },
            "line": 30,
            "name": "user fills in the title with \"Sample Title\"  and the body of the message as \"Body of the message\"",
            "match": {
              "arguments": [
                {
                  "val": "\"Sample Title\"",
                  "offset": 29
                },
                {
                  "val": "\"Body of the message\"",
                  "offset": 76
                }
              ],
              "location": "ActivityStreamStepDefinitions.user_fills_in_the_title_with_and_the_body_of_the_message_as(String,String)"
            },
            "keyword": "And "
          },
          {
            "result": {
              "duration": 4119716125,
              "status": "passed"
            },
            "line": 31,
            "name": "user uploads link to new task",
            "match": {
              "location": "ActivityStreamStepDefinitions.user_uploads_link_to_new_task()"
            },
            "keyword": "Then "
          },
          {
            "result": {
              "duration": 13711753160,
              "status": "passed"
            },
            "line": 32,
            "name": "user picks a deadline",
            "match": {
              "location": "ActivityStreamStepDefinitions.user_picks_a_deadline()"
            },
            "keyword": "Then "
          }
        ],
        "tags": [
          {
            "name": "@Btrix24_activity_stream"
          },
          {
            "name": "@all"
          }
        ]
      }
    ],
    "name": "activity_stream",
    "description": "    As a user I should be able to create a task from activity stream",
    "id": "activity-stream",
    "keyword": "Feature",
    "uri": "src/test/resources/features/activity_stream/Activity_Stream.feature",
    "tags": [
      {
        "name": "@Btrix24_activity_stream",
        "type": "Tag",
        "location": {
          "line": 5,
          "column": 1
        }
      }
    ]
  }
]